pyforgejo/__init__.py
pyforgejo/activitypub/__init__.py
pyforgejo/activitypub/client.py
pyforgejo/activitypub/raw_client.py
pyforgejo/admin/__init__.py
pyforgejo/admin/client.py
pyforgejo/admin/raw_client.py
pyforgejo/admin/types/__init__.py
pyforgejo/admin/types/admin_search_users_request_sort.py
pyforgejo/client.py
pyforgejo/core/__init__.py
pyforgejo/core/api_error.py
pyforgejo/core/client_wrapper.py
pyforgejo/core/datetime_utils.py
pyforgejo/core/file.py
pyforgejo/core/force_multipart.py
pyforgejo/core/http_client.py
pyforgejo/core/http_response.py
pyforgejo/core/jsonable_encoder.py
pyforgejo/core/pydantic_utilities.py
pyforgejo/core/query_encoder.py
pyforgejo/core/remove_none_from_dict.py
pyforgejo/core/request_options.py
pyforgejo/core/serialization.py
pyforgejo/environment.py
pyforgejo/errors/__init__.py
pyforgejo/errors/bad_request_error.py
pyforgejo/errors/conflict_error.py
pyforgejo/errors/content_too_large_error.py
pyforgejo/errors/forbidden_error.py
pyforgejo/errors/internal_server_error.py
pyforgejo/errors/locked_error.py
pyforgejo/errors/method_not_allowed_error.py
pyforgejo/errors/not_found_error.py
pyforgejo/errors/precondition_failed_error.py
pyforgejo/errors/unauthorized_error.py
pyforgejo/errors/unprocessable_entity_error.py
pyforgejo/issue/__init__.py
pyforgejo/issue/client.py
pyforgejo/issue/raw_client.py
pyforgejo/issue/types/__init__.py
pyforgejo/issue/types/create_milestone_option_state.py
pyforgejo/issue/types/issue_list_issues_request_sort.py
pyforgejo/issue/types/issue_list_issues_request_state.py
pyforgejo/issue/types/issue_list_issues_request_type.py
pyforgejo/issue/types/issue_list_labels_request_sort.py
pyforgejo/issue/types/issue_search_issues_request_sort.py
pyforgejo/issue/types/issue_search_issues_request_state.py
pyforgejo/issue/types/issue_search_issues_request_type.py
pyforgejo/miscellaneous/__init__.py
pyforgejo/miscellaneous/client.py
pyforgejo/miscellaneous/raw_client.py
pyforgejo/notification/__init__.py
pyforgejo-2.0.5.dist-info/METADATA
pyforgejo-2.0.5.dist-info/WHEEL
pyforgejo-2.0.5.dist-info/licenses/LICENSE
pyforgejo-2.0.5.dist-info/RECORD
