Metadata-Version: 2.4
Name: pyforgejo
Version: 2.0.5
Summary: A Python client library for accessing the Forgejo API
License-Expression: MIT
License-File: LICENSE
Author: harabat
Requires-Python: >=3.10
Classifier: Programming Language :: Python :: 3
Classifier: Programming Language :: Python :: 3.10
Classifier: Programming Language :: Python :: 3.11
Classifier: Programming Language :: Python :: 3.12
Classifier: Programming Language :: Python :: 3.13
Classifier: Programming Language :: Python :: 3.14
Provides-Extra: dev
Requires-Dist: httpx (>=0.28.1)
Requires-Dist: ipython (>=8.35.0) ; extra == "dev"
Requires-Dist: isort (>=6.0.1) ; extra == "dev"
Requires-Dist: pydantic (>=2.11.2)
Requires-Dist: pytest (>=8.3.5) ; extra == "dev"
Requires-Dist: python-dotenv (>=1.1.0)
Requires-Dist: ruff (>=0.11.4) ; extra == "dev"
Project-URL: Repository, https://codeberg.org/harabat/pyforgejo
